ibis_omniscidb/__init__.py
ibis_omniscidb/_version.py
ibis_omniscidb/client.py
ibis_omniscidb/compiler.py
ibis_omniscidb/ddl.py
ibis_omniscidb/dtypes.py
ibis_omniscidb/geo.py
ibis_omniscidb/identifiers.py
ibis_omniscidb/operations.py
ibis_omniscidb/udf.py
ibis_omniscidb/tests/__init__.py
ibis_omniscidb/tests/conftest.py
ibis_omniscidb/tests/test_client.py
ibis_omniscidb/tests/test_geo.py
ibis_omniscidb/tests/test_operations.py
ibis_omniscidb/tests/test_package.py
ibis_omniscidb/tests/test_udf.py
ibis_omniscidb-2.0.5.dist-info/LICENSE.txt
ibis_omniscidb-2.0.5.dist-info/METADATA
ibis_omniscidb-2.0.5.dist-info/WHEEL
ibis_omniscidb-2.0.5.dist-info/entry_points.txt
ibis_omniscidb-2.0.5.dist-info/top_level.txt
ibis_omniscidb-2.0.5.dist-info/RECORD
