Metadata-Version: 2.1
Name: ibis-omniscidb
Version: 2.0.5
Summary: Ibis OmniSciDB backend
Home-page: https://github.com/omnisci/ibis-omniscidb
Maintainer: OmniSci
Maintainer-email: community@omnisci.com
License: Apache Software License
Platform: UNKNOWN
Classifier: Development Status :: 4 - Beta
Classifier: Operating System :: OS Independent
Classifier: Intended Audience :: Science/Research
Classifier: Programming Language :: Python
Classifier: Programming Language :: Python :: 3
Classifier: Topic :: Scientific/Engineering
Requires-Python: >=3.7
License-File: LICENSE.txt
Requires-Dist: ibis-framework (>=2.0)
Requires-Dist: pandas
Requires-Dist: pyomnisci (>=0.28.1)
Requires-Dist: pyarrow
Requires-Dist: rbc-project (>=0.4.0)
